i2cdev.py
setup.py
i2cdev.egg-info/PKG-INFO
i2cdev.egg-info/SOURCES.txt
i2cdev.egg-info/dependency_links.txt
i2cdev.egg-info/pbr.json
i2cdev.egg-info/top_level.txt