Metadata-Version: 1.1
Name: i2cdev
Version: 1.2.4
Summary: Simple I2C Library for linux
Home-page: https://github.com/cloudformdesign/i2cdev
Author: Garrett Berg
Author-email: garrett@cloudformdesign.com
License: MIT
Platform: Linux
Classifier: Intended Audience :: Developers
Classifier: License :: OSI Approved :: MIT License
Classifier: Operating System :: POSIX :: Linux
Classifier: Programming Language :: Python :: 2.7
Classifier: Programming Language :: Python :: 3
Classifier: Programming Language :: Python :: 3.4
Classifier: Topic :: Software Development :: Libraries :: Python Modules
Classifier: Topic :: System :: Operating System Kernels
Classifier: Topic :: Software Development :: Embedded Systems
Classifier: Topic :: System :: Hardware :: Hardware Drivers
